indicparser/__init__.py
indicparser/langs.py
indicparser/parser.py
indicparser-0.1.0.dist-info/LICENSE
indicparser-0.1.0.dist-info/METADATA
indicparser-0.1.0.dist-info/WHEEL
indicparser-0.1.0.dist-info/top_level.txt
indicparser-0.1.0.dist-info/RECORD
