Metadata-Version: 2.1
Name: indicparser
Version: 0.1.0
Summary: Grapheme Parser for indic languages
Home-page: https://github.com/mnansary/indicparser
Author: Bengali.AI
Author-email: research.bengaliai@gmail.com
License: MIT
Keywords: grapheme,indic languages
Classifier: Development Status :: 5 - Production/Stable
Classifier: Intended Audience :: Education
Classifier: Operating System :: OS Independent
Classifier: License :: OSI Approved :: MIT License
Classifier: Programming Language :: Python :: 3
License-File: LICENSE
